[
  {
    "_id": "5ed20d86f21cb5a012470ac7",
    "name": "Tuttle - Crisman - 38 - WEBIOTIC Transport",
    "price": 89,
    "departure": "2020-05-31 05:40:00.000Z",
    "arrival": "2020-05-31 08:40:00.000Z"
  },
  {
    "_id": "5ed20d94d0986994935e6a00",
    "name": "Venice - Deputy - 34 - SAVVY Transport",
    "price": 428,
    "departure": "2020-06-04T09:00:00+0000",
    "arrival": "2020-06-04T10:00:00+0000"
  },
  {
    "_id": "5ed20dfa817acd4c20987a31",
    "name": "Zagreb - Split - 38 - RIP Klisa Transport",
    "price": 160,
    "departure": "2020-06-06T12:00:00+0000",
    "arrival": "2020-06-06T17:00:00+0000"
  },
  {
    "_id": "5ed20dfe7974408ecd50307f",
    "name": "Venice - Treviso - 34 - SAVVY Transport",
    "price": 30,
    "departure": "2020-06-04T09:15:00+0000",
    "arrival": "2020-06-04T10:00:00+0000"
  }
]
